CHANGES.rst
CONTRIBUTORS.rst
LICENSE.txt
MANIFEST.in
README.rst
requirements.txt
setup.py
docs/Makefile
docs/__init__.py
docs/conf.py
docs/index.rst
docs/api/ltp.checksum_generator.rst
docs/api/ltp.fn_composers.rst
docs/api/ltp.ltp.rst
docs/api/ltp.rst
docs/api/ltp.settings.rst
docs/api/ltp.structures.rst
src/edeposit/__init__.py
src/edeposit.amqp.ltp.egg-info/PKG-INFO
src/edeposit.amqp.ltp.egg-info/SOURCES.txt
src/edeposit.amqp.ltp.egg-info/dependency_links.txt
src/edeposit.amqp.ltp.egg-info/namespace_packages.txt
src/edeposit.amqp.ltp.egg-info/not-zip-safe
src/edeposit.amqp.ltp.egg-info/requires.txt
src/edeposit.amqp.ltp.egg-info/top_level.txt
src/edeposit/amqp/__init__.py
src/edeposit/amqp/ltp/__init__.py
src/edeposit/amqp/ltp/checksum_generator.py
src/edeposit/amqp/ltp/fn_composers.py
src/edeposit/amqp/ltp/info_composer.py
src/edeposit/amqp/ltp/ltp.py
src/edeposit/amqp/ltp/settings.py
src/edeposit/amqp/ltp/amqp_structures/__init__.py
src/edeposit/amqp/ltp/amqp_structures/requests.py
src/edeposit/amqp/ltp/amqp_structures/responses.py
tests/_test_init.py
tests/test_checksum_generator.py
tests/test_fn_composers.py
tests/test_info_composer.py
tests/test_ltp.py
tests/data/hashfile.md5
tests/data/oai_example.oai